wikwork/__init__.py
wikwork/czech.py
wikwork/german.py
wikwork/io_options.py
wikwork/page_media.py
wikwork/parse.py
wikwork/polish.py
wikwork/wrapper.py
wikwork-0.10.0.dist-info/licenses/LICENSE.txt
wikwork-0.10.0.dist-info/METADATA
wikwork-0.10.0.dist-info/WHEEL
wikwork-0.10.0.dist-info/top_level.txt
wikwork-0.10.0.dist-info/RECORD
