Metadata-Version: 2.4
Name: wikwork
Version: 0.10.0
Summary: Use REST APIs to get word and audio file information from Wiktionary™. Pages with audio file information are parsed, as are pages with word information for the German, Polish, and Czech dictionaries. Download of audio files is also supported.
Author-email: Ray Griner <rgriner_fwd@outlook.com>
License:                     GNU GENERAL PUBLIC LICENSE
Keywords: Wiktionary,extract,download,audio
Classifier: Programming Language :: Python :: 3
Classifier: License :: OSI Approved :: GNU General Public License v3 or later (GPLv3+)
Classifier: Operating System :: OS Independent
Classifier: Development Status :: 3 - Alpha
Classifier: Natural Language :: German
Classifier: Natural Language :: Polish
Classifier: Natural Language :: Czech
License-File: LICENSE.txt
Dynamic: license-file
